att_mlops/__init__.py
att_mlops/h2o_mlops_client-0.60.1-py2.py3-none-any.whl
att_mlops/mlflow_registrator.py
att_mlops/mlops_connector.py
att_mlops/mlops_deployer.py
att_mlops-0.1.7.dist-info/METADATA
att_mlops-0.1.7.dist-info/WHEEL
att_mlops-0.1.7.dist-info/RECORD
