Metadata-Version: 2.1
Name: att-mlops
Version: 0.1.7
Summary: 
Author: Your Name
Author-email: you@example.com
Requires-Python: >=3.8,<4.0
Classifier: Programming Language :: Python :: 3
Classifier: Programming Language :: Python :: 3.8
Classifier: Programming Language :: Python :: 3.9
Classifier: Programming Language :: Python :: 3.10
Classifier: Programming Language :: Python :: 3.11
Requires-Dist: mlflow (>=2.2.2,<3.0.0)
